setup.py
pyzmail/__init__.py
pyzmail/generate.py
pyzmail/parse.py
pyzmail/utils.py
pyzmail/version.py
pyzmail39.egg-info/PKG-INFO
pyzmail39.egg-info/SOURCES.txt
pyzmail39.egg-info/dependency_links.txt
pyzmail39.egg-info/top_level.txt
scripts/pyzinfomail
scripts/pyzsendmail