Metadata-Version: 2.1
Name: pyzmail39
Version: 0.0.2
Summary: Python easy mail library, to parse, compose and send emails
Home-page: http://www.magiksys.net/pyzmail
Author: m63
Author-email: m63.dev@gmail.com
License: LGPL
Keywords: email
Platform: UNKNOWN
Classifier: Intended Audience :: Developers
Classifier: License :: OSI Approved :: GNU Library or Lesser General Public License (LGPL)
Classifier: Operating System :: OS Independent
Classifier: Topic :: Communications :: Email
Classifier: Topic :: System :: Networking
Classifier: Topic :: Internet
Classifier: Intended Audience :: Developers
Classifier: Programming Language :: Python
Classifier: Programming Language :: Python :: 3
